setup.py
kcjoshi_distributions/Binomialdistribution.py
kcjoshi_distributions/Gaussiandistribution.py
kcjoshi_distributions/Generaldistribution.py
kcjoshi_distributions/__init__.py
kcjoshi_distributions.egg-info/PKG-INFO
kcjoshi_distributions.egg-info/SOURCES.txt
kcjoshi_distributions.egg-info/dependency_links.txt
kcjoshi_distributions.egg-info/not-zip-safe
kcjoshi_distributions.egg-info/top_level.txt