Metadata-Version: 2.1
Name: kcjoshi-distributions
Version: 0.1
Summary: Gaussian distributions
Author: Keyur Joshi
Author-email: keyur79syd@gmail.com
